BingoRun/__init__.py
BingoRun/module.py
BingoRun-0.1.2.dist-info/LICENSE
BingoRun-0.1.2.dist-info/METADATA
BingoRun-0.1.2.dist-info/WHEEL
BingoRun-0.1.2.dist-info/top_level.txt
BingoRun-0.1.2.dist-info/RECORD
